fig_click_completions/__init__.py
fig_click_completions/fig.py
fig_click_completions-0.0.4.dist-info/LICENSE
fig_click_completions-0.0.4.dist-info/METADATA
fig_click_completions-0.0.4.dist-info/WHEEL
fig_click_completions-0.0.4.dist-info/top_level.txt
fig_click_completions-0.0.4.dist-info/RECORD
