Metadata-Version: 2.1
Name: fig-click-completions
Version: 0.0.4
Summary: Autogenerate Completions for CLI tools built with click
Home-page: https://github.com/withfig/autocomplete-tools
Author: Fig
Author-email: hello@fig.io
License: UNKNOWN
Project-URL: Bug Tracker, https://github.com/withfig/autocomplete-tools/issues
Platform: UNKNOWN
Classifier: Programming Language :: Python :: 3
Classifier: License :: OSI Approved :: MIT License
Classifier: Operating System :: OS Independent
Requires-Python: >=3.6
License-File: LICENSE
Requires-Dist: Click
